<?xml version="1.0" encoding="UTF-8"?>
<con:soapui-project id="cda0bc6b-6712-4c12-b506-daf713fc10c7" activeEnvironment="Default" name="Tharun_168024_RestfulAndSoapWS" resourceRoot="" soapui-version="5.7.0" abortOnError="false" runType="SEQUENTIAL" xmlns:con="http://eviware.com/soapui/config"><con:settings/><con:interface xsi:type="con:RestService" id="90ad06fc-bb50-4d0a-aaf1-b7a0ee1c4be9" wadlVersion="http://wadl.dev.java.net/2009/02" name="http://petstore.swagger.io" type="rest" xmlns:xsi="http://www.w3.org/2001/XMLSchema-instance"><con:settings/><con:definitionCache type="TEXT" rootPart=""/><con:endpoints><con:endpoint>http://petstore.swagger.io</con:endpoint></con:endpoints><con:resource name="Swagger.json" path="/v2/swagger.json" id="af6e8226-8a6e-446d-b712-c899f0f4ec7a"><con:settings/><con:parameters><con:parameter><con:name>_ga</con:name><con:value>2.141582267.849691464.1697632051-398024417.1697632051</con:value><con:style>QUERY</con:style><con:default>2.141582267.849691464.1697632051-398024417.1697632051</con:default><con:path xsi:nil="true"/><con:description xsi:nil="true"/></con:parameter></con:parameters><con:method name="Swagger.json 1" id="85c1c9b6-cc8a-48ac-afd7-dab416cd8b34" method="GET"><con:settings/><con:parameters/><con:representation type="RESPONSE"><con:mediaType>application/json</con:mediaType><con:status>200</con:status><con:params/><con:element xmlns:swag="https://petstore.swagger.io/v2/swagger.json">swag:Response</con:element></con:representation><con:request name="Request 1" id="298b0fa6-c5e6-4771-a959-f516d1b9af80" mediaType="application/json"><con:settings><con:setting id="com.eviware.soapui.impl.wsdl.WsdlRequest@request-headers">&lt;xml-fragment/></con:setting></con:settings><con:endpoint>http://petstore.swagger.io</con:endpoint><con:request/><con:originalUri>https://petstore.swagger.io/v2/swagger.json</con:originalUri><con:credentials><con:authType>No Authorization</con:authType></con:credentials><con:jmsConfig JMSDeliveryMode="PERSISTENT"/><con:jmsPropertyConfig/><con:parameters><entry key="_ga" value="2.141582267.849691464.1697632051-398024417.1697632051" xmlns="http://eviware.com/soapui/config"/></con:parameters><con:parameterOrder><con:entry>_ga</con:entry></con:parameterOrder></con:request></con:method></con:resource></con:interface><con:interface xsi:type="con:RestService" id="ec5dc101-a640-46c5-adeb-e97a33eefa3f" wadlVersion="http://wadl.dev.java.net/2009/02" name="https://petstore.swagger.io" type="rest" xmlns:xsi="http://www.w3.org/2001/XMLSchema-instance"><con:settings/><con:definitionCache type="TEXT" rootPart=""/><con:endpoints><con:endpoint>https://petstore.swagger.io</con:endpoint></con:endpoints><con:resource name="FindByStatus" path="/v2/pet/findByStatus" id="47dd5c30-978c-439b-b032-83c58881ca75"><con:settings/><con:parameters><con:parameter><con:name>status</con:name><con:value>available</con:value><con:style>QUERY</con:style><con:default>available</con:default><con:path xsi:nil="true"/><con:description xsi:nil="true"/></con:parameter></con:parameters><con:method name="FindByStatus 1" id="34f8cf23-d6cd-47f8-9220-f78753b95b6d" method="GET"><con:settings/><con:parameters/><con:representation type="RESPONSE"><con:mediaType>application/json</con:mediaType><con:status>200</con:status><con:params/><con:element>Response</con:element></con:representation><con:request name="Request 1" id="59926734-dd39-4493-9fbe-ea01003e219e" mediaType="application/json"><con:settings><con:setting id="com.eviware.soapui.impl.wsdl.WsdlRequest@request-headers">&lt;xml-fragment/></con:setting></con:settings><con:endpoint>https://petstore.swagger.io</con:endpoint><con:request/><con:originalUri>https://petstore.swagger.io/v2/pet/findByStatus</con:originalUri><con:credentials><con:authType>No Authorization</con:authType></con:credentials><con:jmsConfig JMSDeliveryMode="PERSISTENT"/><con:jmsPropertyConfig/><con:parameters><entry key="status" value="available" xmlns="http://eviware.com/soapui/config"/></con:parameters><con:parameterOrder><con:entry>status</con:entry></con:parameterOrder></con:request></con:method></con:resource></con:interface><con:testSuite id="b63416db-fb59-4b69-b1f2-58ce34897f96" name="TestSuite 1"><con:settings/><con:runType>SEQUENTIAL</con:runType><con:testCase id="daa40bc0-8bd1-482c-8fa8-2f4dcf8c9e55" failOnError="true" failTestCaseOnErrors="true" keepSession="false" maxResults="0" name="TestCase 1" searchProperties="true"><con:settings/><con:testStep type="restrequest" name="Petstore" id="80ce70aa-90c5-4c38-92d1-0cf860fd73d5"><con:settings/><con:config service="https://petstore.swagger.io" resourcePath="/v2/pet/findByStatus" methodName="FindByStatus 1" xsi:type="con:RestRequestStep" xmlns:xsi="http://www.w3.org/2001/XMLSchema-instance"><con:restRequest name="Petstore" id="59926734-dd39-4493-9fbe-ea01003e219e" mediaType="application/json"><con:settings><con:setting id="com.eviware.soapui.impl.wsdl.WsdlRequest@request-headers">&lt;xml-fragment/></con:setting></con:settings><con:endpoint>https://petstore.swagger.io</con:endpoint><con:request/><con:originalUri>https://petstore.swagger.io/v2/pet/findByStatus</con:originalUri><con:assertion type="Response SLA Assertion" id="a8a9ee97-1a38-4d17-9096-a51958d53d15" name="Response SLA"><con:configuration><SLA>10000</SLA></con:configuration></con:assertion><con:assertion type="Sensitive Information Exposure" id="5c3cce46-1467-4859-888e-ce7fd6660cbb" name="Sensitive Information Exposure"><con:configuration><IncludeProjectSpecific>true</IncludeProjectSpecific><IncludeGlobal>true</IncludeGlobal></con:configuration></con:assertion><con:assertion type="JsonPath Count" id="4fc1f16c-9ef7-4a03-96a0-888f53ee0b9b" name="JsonPath Count"><con:configuration/></con:assertion><con:assertion type="Valid HTTP Status Codes" id="761ab57f-1820-4875-99b6-2045653b3885" name="Valid HTTP Status Codes"><con:configuration><codes>200</codes></con:configuration></con:assertion><con:assertion type="Simple Contains" id="18682ee9-60b5-485e-b114-070b61172773" name="Contains"><con:configuration><token>200</token><ignoreCase>false</ignoreCase><useRegEx>false</useRegEx></con:configuration></con:assertion><con:credentials><con:authType>No Authorization</con:authType></con:credentials><con:jmsConfig JMSDeliveryMode="PERSISTENT"/><con:jmsPropertyConfig/><con:parameters><entry key="status" value="available" xmlns="http://eviware.com/soapui/config"/></con:parameters><con:parameterOrder><con:entry>status</con:entry></con:parameterOrder></con:restRequest></con:config></con:testStep><con:properties/></con:testCase><con:properties/></con:testSuite><con:properties/><con:wssContainer/><con:oAuth2ProfileContainer/><con:oAuth1ProfileContainer/><con:sensitiveInformation/></con:soapui-project>